experimaestro_ir-1.4.0.dist-info/licenses/LICENSE
xpmir/__init__.py
xpmir/__main__.py
xpmir/_version.py
xpmir/compat.py
xpmir/context.py
xpmir/distributed.py
xpmir/evaluation.py
xpmir/measures.py
xpmir/misc.py
xpmir/mkdocs_init.py
xpmir/models.py
xpmir/py.typed
xpmir/configuration/__init__.py
xpmir/conversation/__init__.py
xpmir/conversation/learning/__init__.py
xpmir/conversation/learning/reformulation.py
xpmir/conversation/models/__init__.py
xpmir/conversation/models/cosplade.py
xpmir/conversation/models/generative/__init__.py
xpmir/datasets/__init__.py
xpmir/datasets/adapters.py
xpmir/dm/__init__.py
xpmir/dm/config/__init__.py
xpmir/dm/config/ca/__init__.py
xpmir/dm/config/ca/uwaterloo/__init__.py
xpmir/dm/config/ca/uwaterloo/jimmylin/__init__.py
xpmir/dm/config/ca/uwaterloo/jimmylin/anserini.py
xpmir/dm/config/co/huggingface/datasets/sentence-transformers/msmarco-hard-negatives.py
xpmir/dm/config/com/__init__.py
xpmir/dm/config/com/github/sebastian-hofstaetter/neural-ranking-kd.py
xpmir/documents/__init__.py
xpmir/documents/samplers.py
xpmir/experiments/__init__.py
xpmir/experiments/ir.py
xpmir/experiments/learning.py
xpmir/experiments/helpers/__init__.py
xpmir/experiments/helpers/base.py
xpmir/experiments/helpers/launchers.py
xpmir/index/__init__.py
xpmir/index/anserini.py
xpmir/index/faiss.py
xpmir/index/sparse.py
xpmir/interfaces/__init__.py
xpmir/interfaces/anserini.py
xpmir/interfaces/apex.py
xpmir/interfaces/plaintext.py
xpmir/learning/__init__.py
xpmir/learning/base.py
xpmir/learning/batchers.py
xpmir/learning/context.py
xpmir/learning/devices.py
xpmir/learning/hooks.py
xpmir/learning/learner.py
xpmir/learning/losses.py
xpmir/learning/metrics.py
xpmir/learning/optim.py
xpmir/learning/parameters.py
xpmir/learning/schedulers.py
xpmir/learning/trainers/__init__.py
xpmir/learning/trainers/multiple.py
xpmir/learning/trainers/validation.py
xpmir/letor/__init__.py
xpmir/letor/learner.py
xpmir/letor/records.py
xpmir/letor/distillation/__init__.py
xpmir/letor/distillation/pairwise.py
experimaestro_ir-1.4.0.dist-info/METADATA
experimaestro_ir-1.4.0.dist-info/WHEEL
experimaestro_ir-1.4.0.dist-info/entry_points.txt
experimaestro_ir-1.4.0.dist-info/top_level.txt
experimaestro_ir-1.4.0.dist-info/RECORD
