Metadata-Version: 2.4
Name: experimaestro-ir
Version: 1.4.0
Summary: Experimaestro common module for IR experiments
Author-email: Benjamin Piwowarski <benjamin@piwowarski.fr>
License: GPL-3
Project-URL: homepage, https://github.com/bpiwowar/experimaestro-ir
Project-URL: documentation, https://experimaestro-ir.readthedocs.io/en/latest/
Project-URL: repository, https://github.com/bpiwowar/experimaestro-ir
Keywords: neural information retrieval,information retrieval,experiments
Classifier: Development Status :: 4 - Beta
Classifier: Intended Audience :: Science/Research
Classifier: License :: OSI Approved :: GNU General Public License v3 (GPLv3)
Classifier: Operating System :: OS Independent
Classifier: Programming Language :: Python
Classifier: Programming Language :: Python :: 3
Classifier: Topic :: Software Development :: Libraries :: Python Modules
Requires-Python: >=3.10
License-File: LICENSE
Requires-Dist: experimaestro>=1.7.1
Requires-Dist: datamaestro>=1.0.1
Requires-Dist: datamaestro_text>=2024.2.29
Requires-Dist: ir_datasets
Requires-Dist: docstring_parser
Requires-Dist: impact-index==0.27.*
Requires-Dist: omegaconf>=2.2
Requires-Dist: attrs
Requires-Dist: ir-measures>=0.3.3
Requires-Dist: toma
Requires-Dist: pytorch-lightning
Provides-Extra: anserini
Requires-Dist: pyserini>=0.20.0; extra == "anserini"
Provides-Extra: neural
Requires-Dist: torch>=1.12; extra == "neural"
Requires-Dist: tensorboard; extra == "neural"
Requires-Dist: transformers; extra == "neural"
Requires-Dist: sentence_transformers; extra == "neural"
Dynamic: license-file
